website_as_app-1.8.1.dist-info/licenses/LICENSE.md
websiteapp/__init__.py
websiteapp/_version.py
websiteapp/about.py
websiteapp/bookmarks.py
websiteapp/const.py
websiteapp/toolbar.py
websiteapp/utils.py
websiteapp/webapp.py
websiteapp/webengine.py
websiteapp/icons/default.png
websiteapp/icons/logo.png
website_as_app-1.8.1.dist-info/METADATA
website_as_app-1.8.1.dist-info/WHEEL
website_as_app-1.8.1.dist-info/entry_points.txt
website_as_app-1.8.1.dist-info/top_level.txt
website_as_app-1.8.1.dist-info/RECORD
