Metadata-Version: 2.4
Name: website-as-app
Version: 1.8.1
Summary: Opens any web site as standalone desktop app.
Author-email: Marcin Orlowski <mail@marcinOrlowski.com>
License: MIT
Project-URL: Homepage, https://github.com/MarcinOrlowski/website-as-app/
Project-URL: Bug Tracker, https://github.com/MarcinOrlowski/website-as-app/issues/
Project-URL: Documentation, https://github.com/MarcinOrlowski/website-as-app/
Project-URL: Source Code, https://github.com/MarcinOrlowski/website-as-app/
Keywords: webapp,desktop,app
Classifier: Programming Language :: Python :: 3
Classifier: Operating System :: OS Independent
License-File: LICENSE.md
Requires-Dist: argparse>=1.4.0
Requires-Dist: PySide6
Requires-Dist: PyQtWebEngine
Requires-Dist: fasteners
Dynamic: license-file
